README.md
setup.py
brontes/__init__.py
brontes/core.py
brontes.egg-info/PKG-INFO
brontes.egg-info/SOURCES.txt
brontes.egg-info/dependency_links.txt
brontes.egg-info/requires.txt
brontes.egg-info/top_level.txt
brontes/examples/__init__.py
brontes/examples/net.py
brontes/tracker/__init__.py
brontes/tracker/core.py
brontes/tracker/mlflow.py