Metadata-Version: 2.1
Name: brontes
Version: 0.0.2
Summary: Brontes is your helping cyclops for pytorch models training.
Home-page: https://github.com/PhosphorylatedRabbits/brontes
Author: Joris Cadow, Antonio Foncubierta Rodriguez, Matteo Manica
Author-email: joriscadow@gmail.com, antonio.foncubierta@gmail.com, drugilsberg@gmail.com
License: MIT
Platform: UNKNOWN
Classifier: Intended Audience :: Developers
Classifier: Intended Audience :: Science/Research
Classifier: License :: OSI Approved :: MIT License
Classifier: Programming Language :: Python :: 3
Classifier: Programming Language :: Python :: 3.6
Classifier: Programming Language :: Python :: 3.7
Classifier: Topic :: Software Development :: Libraries :: Python Modules
